<?xml version="1.0" encoding="UTF-8"?>
<objects serializationModel="Studio.02.02.00">
	<object class="MixerGroup" id="{bd7ac51a-d7ec-451c-80d5-f758bfaf2c65}">
		<property name="name">
			<value>Music</value>
		</property>
		<relationship name="automators">
			<destination>{faaba692-8627-4d46-8843-f7388642923b}</destination>
		</relationship>
		<relationship name="effectChain">
			<destination>{0b7f7796-220d-4b24-bbe7-e8d70edee59c}</destination>
		</relationship>
		<relationship name="panner">
			<destination>{dec38107-6f22-48bb-aab7-a8f6f82939b9}</destination>
		</relationship>
		<relationship name="output">
			<destination>{b1b0f824-2e17-42ca-8c4a-48fa53894a72}</destination>
		</relationship>
	</object>
	<object class="Automator" id="{faaba692-8627-4d46-8843-f7388642923b}">
		<property name="nameOfPropertyBeingAutomated">
			<value>volume</value>
		</property>
		<relationship name="automationCurves">
			<destination>{917f96cd-7b82-4f87-9758-918ddf547fe8}</destination>
		</relationship>
	</object>
	<object class="MixerBusEffectChain" id="{0b7f7796-220d-4b24-bbe7-e8d70edee59c}">
		<relationship name="effects">
			<destination>{457c69b5-c8e7-4f3d-87bf-ffeedc5de1ce}</destination>
		</relationship>
	</object>
	<object class="MixerBusPanner" id="{dec38107-6f22-48bb-aab7-a8f6f82939b9}">
		<property name="overridingOutputFormat">
			<value>1</value>
		</property>
	</object>
	<object class="AutomationCurve" id="{917f96cd-7b82-4f87-9758-918ddf547fe8}">
		<relationship name="parameter">
			<destination>{647511e2-1cb2-4fef-9962-846cbc407435}</destination>
		</relationship>
		<relationship name="automationPoints">
			<destination>{92d233f3-fc5c-43cb-ad59-bfb20eab15c1}</destination>
			<destination>{878168d6-8281-4973-ab98-1584ce846156}</destination>
		</relationship>
	</object>
	<object class="MixerBusFader" id="{457c69b5-c8e7-4f3d-87bf-ffeedc5de1ce}" />
	<object class="AutomationPoint" id="{92d233f3-fc5c-43cb-ad59-bfb20eab15c1}">
		<property name="position">
			<value>0</value>
		</property>
		<property name="value">
			<value>-52.5</value>
		</property>
		<property name="curveShape">
			<value>-0.173828125</value>
		</property>
	</object>
	<object class="AutomationPoint" id="{878168d6-8281-4973-ab98-1584ce846156}">
		<property name="position">
			<value>1</value>
		</property>
		<property name="value">
			<value>5.25</value>
		</property>
	</object>
</objects>
